[
    {
        "1": "Русский язык",
        "2": "Литература",
        "3": "Математика",
        "4": "Биология",
        "5": "Биология",
        "6": "Английский язык",
        "7": "Английский язык",
        "8": "Английский язык",
        "9": "",
        "10": "",
        "11": ""
    },
    {
        "1": "Химия",
        "2": "Математика",
        "3": "Физическая культура",
        "4": "ОБЖ",
        "5": "Физика",
        "6": "Технология",
        "7": "Занимательный русский",
        "8": "Юный химик / Основные вопросы математики",
        "9": "Спортивные игры / Основные вопросы математики",
        "10": "",
        "11": ""
    },
    {
        "1": "Химия",
        "2": "География",
        "3": "Математика",
        "4": "География",
        "5": "Информатика",
        "6": "Мир информатики",
        "7": "Физическая культура",
        "8": "Юный математик / Грамматика английского языка",
        "9": "Мир профессий / Занимательный русский",
        "10": "",
        "11": ""
    },
    {
        "1": "История",
        "2": "Литература",
        "3": "Русский язык",
        "4": "Физика",
        "5": "Математика",
        "6": "Родной язык (русский)",
        "7": "Обществознание",
        "8": "",
        "9": "",
        "10": "",
        "11": ""
    },
    {
        "1": "История",
        "2": "Русский язык",
        "3": "Математика",
        "4": "Физика",
        "5": "Литература",
        "6": "Психолог",
        "7": "",
        "8": "",
        "9": "",
        "10": "",
        "11": ""
    }
]